SPI_master.v
// SPI Master without chip select

module spi_master (i_RST_L , i_Clk , i_TX_Byte , i_TX_DV , o_RX_Byte , o_RX_DV , o_TX_Ready , i_SPI_MISO , o_SPI_Clk , o_SPI_MOSI ) ;

parameter SPI_Mode = 0 ;
parameter CLKS_PER_HALF_BIT = 2 ;

input i_RST_L , i_Clk , i_TX_DV ;
input [7:0] i_TX_Byte ;
input  i_SPI_MISO ;

output reg o_RX_DV , o_TX_Ready ;
output reg [7:0] o_RX_Byte ;
output reg o_SPI_Clk ;
output reg o_SPI_MOSI ;

// SPI Interface (all of these below runs on SPI Clock ie SCLK and not i_Clk)

wire CPOL ;
wire CPHA ;

reg [3:0] r_SPI_Clk_Count ;
reg r_SPI_Clk ;                // To store the clock of SPI before giving it to "o_SPI_Clk" 
reg [4:0] r_SPI_Clk_Edges ;    // 1 bit has 2 clock edges , so 8 bit has 16 clock edges (FOR CLOCK)
reg r_Leading_Edge ;
reg r_Trailing_Edge ;
reg r_TX_DV ;           // Basically stores "i_TX_DV" signal
reg [7:0] r_TX_Byte ;  // Basically stores "i_TX_Byte" data
reg [2:0] r_RX_Bit_Count ;   // Counter to count no. of bits received from MISO  (Receiving 1 bit per SPI clock)
reg [2:0] r_TX_Bit_Count ;   // Counter to count no. of bits transferred via MOSI (Transmitting 1 bit per SPI clock)

assign CPOL = (SPI_Mode == 2 || SPI_Mode == 3) ;
assign CPHA = (SPI_Mode == 1 || SPI_Mode == 3) ;


// TO GENERATE SPI CLOCK ( SCLK ) correct number of times when DV pulse comes (SO I AM INTERESTED IN THOSE VARIABLES RELATED WITH CLOCK)
// generates the SPI clock and controls when leading and trailing edges happen
always @ (posedge i_Clk or negedge i_RST_L)
    begin
        if (~i_RST_L)
            begin
                o_TX_Ready <= 0 ;
                r_SPI_Clk_Edges <= 0 ;
                r_Leading_Edge <= 0 ;
                r_Trailing_Edge <= 0 ;
                r_SPI_Clk <= CPOL ;   // Set Clock to its Ideal state
                r_SPI_Clk_Count <= 0 ;
            end
        
        else
            begin
                r_Leading_Edge <= 0 ;
                r_Trailing_Edge <= 0 ;

                if (i_TX_DV) 
                    begin
                        o_TX_Ready <= 0 ;
                        r_SPI_Clk_Edges <= 16 ;
                    end

                else if (r_SPI_Clk_Edges > 0)
                    begin
                        o_TX_Ready <= 0 ;

                        // Trailing Edge Condition
                        if (r_SPI_Clk_Count == (CLKS_PER_HALF_BIT*2 - 1))
                            begin
                                r_SPI_Clk_Edges <= r_SPI_Clk_Edges - 1 ;
                                r_Trailing_Edge <= 1'b1 ;
                                r_SPI_Clk_Count <= 0 ;
                                r_SPI_Clk <= ~ r_SPI_Clk ;
                            end

                        // Leading Edge Condition
                        else if (r_SPI_Clk_Count == (CLKS_PER_HALF_BIT - 1)) 
                            begin
                                r_SPI_Clk_Edges <= r_SPI_Clk_Edges - 1 ;
                                r_Leading_Edge <= 1'b1 ;
                                r_SPI_Clk_Count <= r_SPI_Clk_Count + 1 ;
                                r_SPI_Clk <= ~ r_SPI_Clk ;
                            end   

                        else
                            begin
                                r_SPI_Clk_Count <= r_SPI_Clk_Count + 1 ;  // No toggle yet → Just increment the counter
                            end    
                    end    
                
                else    
                    begin
                        o_TX_Ready <= 1'b1 ;    // When All Edges (16 edges since data is of 8 bits) Are Done (Transmission Complete)
                    end  
            end
    end

// This block captures the input byte "i_TX_Byte" into "r_TX_Byte" only when "i_TX_DV" is high, ensuring stable data during SPI transmission.
// It also delays "i_TX_DV" by 1 cycle into "r_TX_DV" to align timing with the rest of the logic.
always @ (posedge i_Clk or negedge i_RST_L) 
    begin
        if (~i_RST_L)
            begin
                r_TX_Byte <= 8'b0 ;
                r_TX_DV <= 0 ;
            end

        else
            begin
                r_TX_DV <= i_TX_DV ;  // Why? Because other blocks (like the MOSI logic) use "r_TX_DV", not "i_TX_DV", to avoid timing mismatch or race conditions
                if (i_TX_DV)
                    begin
                        r_TX_Byte <= i_TX_Byte ;
                    end
            end
    end 

// This block handles sending data bit by bit on the MOSI line
// It's built to handle both SPI modes with CPHA = 0 and CPHA = 1
always @ (posedge i_Clk or negedge i_RST_L)
    begin
        if (~i_RST_L)
            begin
                o_SPI_MOSI <= 0 ;            // clear the MOSI line
                r_TX_Bit_Count <= 3'b111 ;  // prepares to send the Most Significant Bit first
            end
        
        else
            begin
                // CASE 1 :  Ensures "r_TX_Bit_Count" is reset to 7 whenever "o_TX_Ready" is high — meaning transmission just completed and the master is now ready for a new byte.
                if (o_TX_Ready)
                    begin
                        r_TX_Bit_Count <= 3'b111 ;
                    end
                
                // CASE 2 :  Is mandatory to support SPI Mode 0 and Mode 2 (where CPHA = 0), because it ensures that the first bit is on the line before the first SPI clock edge occurs. Without this, the very first bit received by the slave would be invalid.
                else if (r_TX_DV & ~CPHA)
                    begin
                        o_SPI_MOSI <= r_TX_Byte[7] ;
                        r_TX_Bit_Count <= 3'b110 ;
                    end

                // CASE 3 : Continue shifting out remaining bits
                else if ((r_Leading_Edge & CPHA) | (r_Trailing_Edge & ~CPHA)) 
                    begin
                        r_TX_Bit_Count <= r_TX_Bit_Count - 1 ;
                        o_SPI_MOSI <= r_TX_Byte[r_TX_Bit_Count] ;
                    end   

            end
    end

// This block samples incoming MISO data bit-by-bit on the correct SPI clock edge, stores it into a register, and raises a data-valid pulse ("o_RX_DV") once the full 8-bit byte is received.
always @ (posedge i_Clk or negedge i_RST_L)
    begin
        if (~i_RST_L)
            begin
                o_RX_Byte <= 8'b0 ;
                o_RX_DV <= 0 ;
                r_RX_Bit_Count <= 3'b111 ;
            end

        else 
            begin
                o_RX_DV <= 1'b0 ;  // This ensures that the data-valid pulse is only high for one clock cycle when we finish a byte.
                
                if (o_TX_Ready)
                    begin
                        r_RX_Bit_Count <= 3'b111 ;
                    end

                else if ((r_Leading_Edge & ~CPHA) | (r_Trailing_Edge & CPHA))
                    begin
                        r_RX_Bit_Count <= r_RX_Bit_Count - 1 ;
                        o_RX_Byte[r_RX_Bit_Count] <= i_SPI_MISO ;

                        if (r_RX_Bit_Count == 0)
                            begin
                                o_RX_DV <= 1'b1 ;
                            end
                    end
                    
            end    
    end

// This block delays the SPI clock output by one FPGA clock cycle to align it with the rest of the output signals, especially MOSI.
always @ (posedge i_Clk or negedge i_RST_L) 
    begin
        if (~i_RST_L)
            begin
                o_SPI_Clk <= CPOL ;
            end
        
        else
            begin
                o_SPI_Clk <= r_SPI_Clk ;
            end
    end

endmodule

test_bench_spi.v
`timescale 1ns / 1ps

module spi_master_TB;

  parameter SPI_MODE = 3;             // CPOL = 1, CPHA = 1
  parameter CLKS_PER_HALF_BIT = 4;    // For 6.25 MHz SPI Clock
  parameter MAIN_CLK_DELAY = 2;       // 25 MHz Main Clock = 40 ns

  reg r_Rst_L = 1'b0;
  reg r_Clk   = 1'b0;

  // SPI Interface Signals
  wire w_SPI_Clk;
  wire w_SPI_MOSI;

  reg  [7:0] r_Master_TX_Byte = 8'h00;
  reg        r_Master_TX_DV   = 1'b0;
  wire       w_Master_TX_Ready;
  wire       r_Master_RX_DV;
  wire [7:0] r_Master_RX_Byte;

  // Clock Generator
  always #(MAIN_CLK_DELAY) r_Clk = ~r_Clk;

  // Instantiate the DUT (Device Under Test)
  spi_master #(
    .SPI_Mode(SPI_MODE),
    .CLKS_PER_HALF_BIT(CLKS_PER_HALF_BIT)
  ) dut (
    .i_RST_L(r_Rst_L),
    .i_Clk(r_Clk),

    // Transmit signals
    .i_TX_Byte(r_Master_TX_Byte),
    .i_TX_DV(r_Master_TX_DV),
    .o_TX_Ready(w_Master_TX_Ready),

    // Receive signals
    .o_RX_DV(r_Master_RX_DV),
    .o_RX_Byte(r_Master_RX_Byte),

    // SPI signals
    .o_SPI_Clk(w_SPI_Clk),
    .i_SPI_MISO(w_SPI_MOSI),   // Loopback
    .o_SPI_MOSI(w_SPI_MOSI)
  );

  // Test Sequence
  initial begin
    // VCD file for waveform viewing
    $dumpfile("spi.vcd");
    $dumpvars(0, spi_master_TB);

    // Initial reset
    repeat(10) @(posedge r_Clk);
    r_Rst_L = 1'b0;
    repeat(10) @(posedge r_Clk);
    r_Rst_L = 1'b1;

    // --- Send Byte 0xC1 ---
    @(posedge r_Clk);
    r_Master_TX_Byte <= 8'hC1;
    r_Master_TX_DV   <= 1'b1;
    @(posedge r_Clk);
    r_Master_TX_DV   <= 1'b0;
    @(posedge w_Master_TX_Ready);
    $display("Sent 0xC1, Received 0x%02X", r_Master_RX_Byte);

    // --- Send Byte 0xBE ---
    @(posedge r_Clk);
    r_Master_TX_Byte <= 8'hBE;
    r_Master_TX_DV   <= 1'b1;
    @(posedge r_Clk);
    r_Master_TX_DV   <= 1'b0;
    @(posedge w_Master_TX_Ready);
    $display("Sent 0xBE, Received 0x%02X", r_Master_RX_Byte);

    // --- Send Byte 0xEF ---
    @(posedge r_Clk);
    r_Master_TX_Byte <= 8'hEF;
    r_Master_TX_DV   <= 1'b1;
    @(posedge r_Clk);
    r_Master_TX_DV   <= 1'b0;
    @(posedge w_Master_TX_Ready);
    $display("Sent 0xEF, Received 0x%02X", r_Master_RX_Byte);

    repeat(10) @(posedge r_Clk);
    $display("Simulation completed successfully.");
    $finish;
  end

endmodule

spi.vcd
$date
	Fri Jun 27 00:56:14 2025
$end
$version
	Icarus Verilog
$end
$timescale
	1ps
$end
$scope module spi_master_TB $end
$var wire 1 ! w_SPI_MOSI $end
$var wire 1 " w_SPI_Clk $end
$var wire 1 # w_Master_TX_Ready $end
$var wire 1 $ r_Master_RX_DV $end
$var wire 8 % r_Master_RX_Byte [7:0] $end
$var parameter 32 & CLKS_PER_HALF_BIT $end
$var parameter 32 ' MAIN_CLK_DELAY $end
$var parameter 32 ( SPI_MODE $end
$var reg 1 ) r_Clk $end
$var reg 8 * r_Master_TX_Byte [7:0] $end
$var reg 1 + r_Master_TX_DV $end
$var reg 1 , r_Rst_L $end
$scope module dut $end
$var wire 1 - CPHA $end
$var wire 1 . CPOL $end
$var wire 1 ) i_Clk $end
$var wire 1 , i_RST_L $end
$var wire 8 / i_TX_Byte [7:0] $end
$var wire 1 + i_TX_DV $end
$var wire 1 ! i_SPI_MISO $end
$var parameter 32 0 CLKS_PER_HALF_BIT $end
$var parameter 32 1 SPI_Mode $end
$var reg 8 2 o_RX_Byte [7:0] $end
$var reg 1 $ o_RX_DV $end
$var reg 1 " o_SPI_Clk $end
$var reg 1 ! o_SPI_MOSI $end
$var reg 1 # o_TX_Ready $end
$var reg 1 3 r_Leading_Edge $end
$var reg 3 4 r_RX_Bit_Count [2:0] $end
$var reg 1 5 r_SPI_Clk $end
$var reg 4 6 r_SPI_Clk_Count [3:0] $end
$var reg 5 7 r_SPI_Clk_Edges [4:0] $end
$var reg 3 8 r_TX_Bit_Count [2:0] $end
$var reg 8 9 r_TX_Byte [7:0] $end
$var reg 1 : r_TX_DV $end
$var reg 1 ; r_Trailing_Edge $end
$upscope $end
$upscope $end
$enddefinitions $end
$comment Show the parameter values. $end
$dumpall
b11 1
b100 0
b11 (
b10 '
b100 &
$end
#0
$dumpvars
0;
0:
b0 9
b111 8
b0 7
b0 6
15
b111 4
03
b0 2
b0 /
1.
1-
0,
0+
b0 *
0)
b0 %
0$
0#
1"
0!
$end
#2000
1)
#4000
0)
#6000
1)
#8000
0)
#10000
1)
#12000
0)
#14000
1)
#16000
0)
#18000
1)
#20000
0)
#22000
1)
#24000
0)
#26000
1)
#28000
0)
#30000
1)
#32000
0)
#34000
1)
#36000
0)
#38000
1)
#40000
0)
#42000
1)
#44000
0)
#46000
1)
#48000
0)
#50000
1)
#52000
0)
#54000
1)
#56000
0)
#58000
1)
#60000
0)
#62000
1)
#64000
0)
#66000
1)
#68000
0)
#70000
1)
#72000
0)
#74000
1)
#76000
0)
#78000
1#
1,
1)
#80000
0)
#82000
1+
b11000001 *
b11000001 /
1)
#84000
0)
#86000
b10000 7
0#
b11000001 9
1:
0+
1)
#88000
0)
#90000
0:
b1 6
1)
#92000
0)
#94000
b10 6
1)
#96000
0)
#98000
b11 6
1)
#100000
0)
#102000
05
b100 6
13
b1111 7
1)
#104000
0)
#106000
0"
1!
b110 8
b101 6
03
1)
#108000
0)
#110000
b110 6
1)
#112000
0)
#114000
b111 6
1)
#116000
0)
#118000
15
b0 6
1;
b1110 7
1)
#120000
0)
#122000
1"
b10000000 %
b10000000 2
b110 4
b1 6
0;
1)
#124000
0)
#126000
b10 6
1)
#128000
0)
#130000
b11 6
1)
#132000
0)
#134000
05
b100 6
13
b1101 7
1)
#136000
0)
#138000
0"
b101 8
b101 6
03
1)
#140000
0)
#142000
b110 6
1)
#144000
0)
#146000
b111 6
1)
#148000
0)
#150000
15
b0 6
1;
b1100 7
1)
#152000
0)
#154000
1"
b11000000 %
b11000000 2
b101 4
b1 6
0;
1)
#156000
0)
#158000
b10 6
1)
#160000
0)
#162000
b11 6
1)
#164000
0)
#166000
05
b100 6
13
b1011 7
1)
#168000
0)
#170000
0"
0!
b100 8
b101 6
03
1)
#172000
0)
#174000
b110 6
1)
#176000
0)
#178000
b111 6
1)
#180000
0)
#182000
15
b0 6
1;
b1010 7
1)
#184000
0)
#186000
1"
b100 4
b1 6
0;
1)
#188000
0)
#190000
b10 6
1)
#192000
0)
#194000
b11 6
1)
#196000
0)
#198000
05
b100 6
13
b1001 7
1)
#200000
0)
#202000
0"
b11 8
b101 6
03
1)
#204000
0)
#206000
b110 6
1)
#208000
0)
#210000
b111 6
1)
#212000
0)
#214000
15
b0 6
1;
b1000 7
1)
#216000
0)
#218000
1"
b11 4
b1 6
0;
1)
#220000
0)
#222000
b10 6
1)
#224000
0)
#226000
b11 6
1)
#228000
0)
#230000
05
b100 6
13
b111 7
1)
#232000
0)
#234000
0"
b10 8
b101 6
03
1)
#236000
0)
#238000
b110 6
1)
#240000
0)
#242000
b111 6
1)
#244000
0)
#246000
15
b0 6
1;
b110 7
1)
#248000
0)
#250000
1"
b10 4
b1 6
0;
1)
#252000
0)
#254000
b10 6
1)
#256000
0)
#258000
b11 6
1)
#260000
0)
#262000
05
b100 6
13
b101 7
1)
#264000
0)
#266000
0"
b1 8
b101 6
03
1)
#268000
0)
#270000
b110 6
1)
#272000
0)
#274000
b111 6
1)
#276000
0)
#278000
15
b0 6
1;
b100 7
1)
#280000
0)
#282000
1"
b1 4
b1 6
0;
1)
#284000
0)
#286000
b10 6
1)
#288000
0)
#290000
b11 6
1)
#292000
0)
#294000
05
b100 6
13
b11 7
1)
#296000
0)
#298000
0"
b0 8
b101 6
03
1)
#300000
0)
#302000
b110 6
1)
#304000
0)
#306000
b111 6
1)
#308000
0)
#310000
15
b0 6
1;
b10 7
1)
#312000
0)
#314000
1"
b0 4
b1 6
0;
1)
#316000
0)
#318000
b10 6
1)
#320000
0)
#322000
b11 6
1)
#324000
0)
#326000
05
b100 6
13
b1 7
1)
#328000
0)
#330000
0"
1!
b111 8
b101 6
03
1)
#332000
0)
#334000
b110 6
1)
#336000
0)
#338000
b111 6
1)
#340000
0)
#342000
15
b0 6
1;
b0 7
1)
#344000
0)
#346000
1"
1$
b11000001 %
b11000001 2
b111 4
1#
0;
1)
#348000
0)
#350000
0$
1+
b10111110 *
b10111110 /
1)
#352000
0)
#354000
b10111110 9
1:
b10000 7
0#
0+
1)
#356000
0)
#358000
b1 6
0:
1)
#360000
0)
#362000
b10 6
1)
#364000
0)
#366000
b11 6
1)
#368000
0)
#370000
05
b100 6
13
b1111 7
1)
#372000
0)
#374000
b101 6
03
b110 8
0"
1)
#376000
0)
#378000
b110 6
1)
#380000
0)
#382000
b111 6
1)
#384000
0)
#386000
15
b0 6
1;
b1110 7
1)
#388000
0)
#390000
b1 6
0;
b110 4
1"
1)
#392000
0)
#394000
b10 6
1)
#396000
0)
#398000
b11 6
1)
#400000
0)
#402000
05
b100 6
13
b1101 7
1)
#404000
0)
#406000
b101 6
03
0!
b101 8
0"
1)
#408000
0)
#410000
b110 6
1)
#412000
0)
#414000
b111 6
1)
#416000
0)
#418000
15
b0 6
1;
b1100 7
1)
#420000
0)
#422000
b1 6
0;
b10000001 %
b10000001 2
b101 4
1"
1)
#424000
0)
#426000
b10 6
1)
#428000
0)
#430000
b11 6
1)
#432000
0)
#434000
05
b100 6
13
b1011 7
1)
#436000
0)
#438000
b101 6
03
1!
b100 8
0"
1)
#440000
0)
#442000
b110 6
1)
#444000
0)
#446000
b111 6
1)
#448000
0)
#450000
15
b0 6
1;
b1010 7
1)
#452000
0)
#454000
b1 6
0;
b10100001 %
b10100001 2
b100 4
1"
1)
#456000
0)
#458000
b10 6
1)
#460000
0)
#462000
b11 6
1)
#464000
0)
#466000
05
b100 6
13
b1001 7
1)
#468000
0)
#470000
b101 6
03
b11 8
0"
1)
#472000
0)
#474000
b110 6
1)
#476000
0)
#478000
b111 6
1)
#480000
0)
#482000
15
b0 6
1;
b1000 7
1)
#484000
0)
#486000
b1 6
0;
b10110001 %
b10110001 2
b11 4
1"
1)
#488000
0)
#490000
b10 6
1)
#492000
0)
#494000
b11 6
1)
#496000
0)
#498000
05
b100 6
13
b111 7
1)
#500000
0)
#502000
b101 6
03
b10 8
0"
1)
#504000
0)
#506000
b110 6
1)
#508000
0)
#510000
b111 6
1)
#512000
0)
#514000
15
b0 6
1;
b110 7
1)
#516000
0)
#518000
b1 6
0;
b10111001 %
b10111001 2
b10 4
1"
1)
#520000
0)
#522000
b10 6
1)
#524000
0)
#526000
b11 6
1)
#528000
0)
#530000
05
b100 6
13
b101 7
1)
#532000
0)
#534000
b101 6
03
b1 8
0"
1)
#536000
0)
#538000
b110 6
1)
#540000
0)
#542000
b111 6
1)
#544000
0)
#546000
15
b0 6
1;
b100 7
1)
#548000
0)
#550000
b1 6
0;
b10111101 %
b10111101 2
b1 4
1"
1)
#552000
0)
#554000
b10 6
1)
#556000
0)
#558000
b11 6
1)
#560000
0)
#562000
05
b100 6
13
b11 7
1)
#564000
0)
#566000
b101 6
03
b0 8
0"
1)
#568000
0)
#570000
b110 6
1)
#572000
0)
#574000
b111 6
1)
#576000
0)
#578000
15
b0 6
1;
b10 7
1)
#580000
0)
#582000
b1 6
0;
b10111111 %
b10111111 2
b0 4
1"
1)
#584000
0)
#586000
b10 6
1)
#588000
0)
#590000
b11 6
1)
#592000
0)
#594000
05
b100 6
13
b1 7
1)
#596000
0)
#598000
b101 6
03
0!
b111 8
0"
1)
#600000
0)
#602000
b110 6
1)
#604000
0)
#606000
b111 6
1)
#608000
0)
#610000
15
b0 6
1;
b0 7
1)
#612000
0)
#614000
1#
0;
1$
b10111110 %
b10111110 2
b111 4
1"
1)
#616000
0)
#618000
0$
1+
b11101111 *
b11101111 /
1)
#620000
0)
#622000
b10000 7
0#
b11101111 9
1:
0+
1)
#624000
0)
#626000
0:
b1 6
1)
#628000
0)
#630000
b10 6
1)
#632000
0)
#634000
b11 6
1)
#636000
0)
#638000
05
b100 6
13
b1111 7
1)
#640000
0)
#642000
0"
1!
b110 8
b101 6
03
1)
#644000
0)
#646000
b110 6
1)
#648000
0)
#650000
b111 6
1)
#652000
0)
#654000
15
b0 6
1;
b1110 7
1)
#656000
0)
#658000
1"
b110 4
b1 6
0;
1)
#660000
0)
#662000
b10 6
1)
#664000
0)
#666000
b11 6
1)
#668000
0)
#670000
05
b100 6
13
b1101 7
1)
#672000
0)
#674000
0"
b101 8
b101 6
03
1)
#676000
0)
#678000
b110 6
1)
#680000
0)
#682000
b111 6
1)
#684000
0)
#686000
15
b0 6
1;
b1100 7
1)
#688000
0)
#690000
1"
b11111110 %
b11111110 2
b101 4
b1 6
0;
1)
#692000
0)
#694000
b10 6
1)
#696000
0)
#698000
b11 6
1)
#700000
0)
#702000
05
b100 6
13
b1011 7
1)
#704000
0)
#706000
0"
b100 8
b101 6
03
1)
#708000
0)
#710000
b110 6
1)
#712000
0)
#714000
b111 6
1)
#716000
0)
#718000
15
b0 6
1;
b1010 7
1)
#720000
0)
#722000
1"
b100 4
b1 6
0;
1)
#724000
0)
#726000
b10 6
1)
#728000
0)
#730000
b11 6
1)
#732000
0)
#734000
05
b100 6
13
b1001 7
1)
#736000
0)
#738000
0"
0!
b11 8
b101 6
03
1)
#740000
0)
#742000
b110 6
1)
#744000
0)
#746000
b111 6
1)
#748000
0)
#750000
15
b0 6
1;
b1000 7
1)
#752000
0)
#754000
1"
b11101110 %
b11101110 2
b11 4
b1 6
0;
1)
#756000
0)
#758000
b10 6
1)
#760000
0)
#762000
b11 6
1)
#764000
0)
#766000
05
b100 6
13
b111 7
1)
#768000
0)
#770000
0"
1!
b10 8
b101 6
03
1)
#772000
0)
#774000
b110 6
1)
#776000
0)
#778000
b111 6
1)
#780000
0)
#782000
15
b0 6
1;
b110 7
1)
#784000
0)
#786000
1"
b10 4
b1 6
0;
1)
#788000
0)
#790000
b10 6
1)
#792000
0)
#794000
b11 6
1)
#796000
0)
#798000
05
b100 6
13
b101 7
1)
#800000
0)
#802000
0"
b1 8
b101 6
03
1)
#804000
0)
#806000
b110 6
1)
#808000
0)
#810000
b111 6
1)
#812000
0)
#814000
15
b0 6
1;
b100 7
1)
#816000
0)
#818000
1"
b1 4
b1 6
0;
1)
#820000
0)
#822000
b10 6
1)
#824000
0)
#826000
b11 6
1)
#828000
0)
#830000
05
b100 6
13
b11 7
1)
#832000
0)
#834000
0"
b0 8
b101 6
03
1)
#836000
0)
#838000
b110 6
1)
#840000
0)
#842000
b111 6
1)
#844000
0)
#846000
15
b0 6
1;
b10 7
1)
#848000
0)
#850000
1"
b0 4
b1 6
0;
1)
#852000
0)
#854000
b10 6
1)
#856000
0)
#858000
b11 6
1)
#860000
0)
#862000
05
b100 6
13
b1 7
1)
#864000
0)
#866000
0"
b111 8
b101 6
03
1)
#868000
0)
#870000
b110 6
1)
#872000
0)
#874000
b111 6
1)
#876000
0)
#878000
15
b0 6
1;
b0 7
1)
#880000
0)
#882000
1"
1$
b11101111 %
b11101111 2
b111 4
1#
0;
1)
#884000
0)
#886000
0$
1)
